odoo/addons/web_searchbar_full_width/README.rst
odoo/addons/web_searchbar_full_width/__init__.py
odoo/addons/web_searchbar_full_width/__manifest__.py
odoo/addons/web_searchbar_full_width/i18n/web_searchbar_full_width.pot
odoo/addons/web_searchbar_full_width/static/description/icon.png
odoo/addons/web_searchbar_full_width/static/description/preview.png
odoo/addons/web_searchbar_full_width/static/src/css/web_searchbar_full_width.css
odoo/addons/web_searchbar_full_width/views/templates.xml
odoo11_addon_web_searchbar_full_width-11.0.1.0.1.dist-info/METADATA
odoo11_addon_web_searchbar_full_width-11.0.1.0.1.dist-info/WHEEL
odoo11_addon_web_searchbar_full_width-11.0.1.0.1.dist-info/top_level.txt
odoo11_addon_web_searchbar_full_width-11.0.1.0.1.dist-info/RECORD
