Metadata-Version: 2.1
Name: odoo11-addon-web-searchbar-full-width
Version: 11.0.1.0.1
Summary: Show search bar in full screen width
Home-page: https://github.com/OCA/web
Author: Therp BV, Odoo Community Association (OCA), Siddharth Bhalgami
Author-email: support@odoo-community.org
License: AGPL-3
Platform: UNKNOWN
Classifier: Programming Language :: Python
Classifier: Framework :: Odoo
Classifier: Framework :: Odoo :: 11.0
Classifier: License :: OSI Approved :: GNU Affero General Public License v3
Requires-Python: >=2.7, !=3.0.*, !=3.1.*, !=3.2.*, !=3.3.*, !=3.4.*
Requires-Dist: odoo <11.1dev,>=11.0a
